[
  {
    "full_name": "lowerbarriers/finished-starter",
    "stargazers_count": 34,
    "open_issues_count": 9,
    "forks_count": 10
  },
  {
    "full_name": "benbusby/whoogle-search",
    "stargazers_count": 5469,
    "open_issues_count": 49,
    "forks_count": 609
  },
  {
    "full_name": "knadh/listmonk",
    "stargazers_count": 8092,
    "open_issues_count": 58,
    "forks_count": 603
  },
  {
    "full_name": "pre-commit/pre-commit",
    "stargazers_count": 8179,
    "open_issues_count": 20,
    "forks_count": 606
  },
  {
    "full_name": "sourcery-ai/sourcery",
    "stargazers_count": 844,
    "open_issues_count": 42,
    "forks_count": 33
  },
  {
    "full_name": "github-craftwork/start-here",
    "stargazers_count": 87,
    "open_issues_count": 2,
    "forks_count": 100
  },
  {
    "full_name": "pyenv-win/pyenv-win",
    "stargazers_count": 1518,
    "open_issues_count": 80,
    "forks_count": 171
  },
  {
    "full_name": "sdras/awesome-actions",
    "stargazers_count": 17848,
    "open_issues_count": 92,
    "forks_count": 1189
  },
  {
    "full_name": "mdn/content",
    "stargazers_count": 5523,
    "open_issues_count": 705,
    "forks_count": 9112
  },
  {
    "full_name": "mazipan/hello-open-source",
    "stargazers_count": 388,
    "open_issues_count": 4,
    "forks_count": 397
  },
  {
    "full_name": "jramirez857/email-cleaner",
    "stargazers_count": 2,
    "open_issues_count": 2,
    "forks_count": 1
  },
  {
    "full_name": "bigskysoftware/htmx",
    "stargazers_count": 6803,
    "open_issues_count": 106,
    "forks_count": 267
  },
  {
    "full_name": "zawad2221/Twitter-Django-Bot",
    "stargazers_count": 8,
    "open_issues_count": 0,
    "forks_count": 1
  },
  {
    "full_name": "asottile/pyupgrade",
    "stargazers_count": 1755,
    "open_issues_count": 15,
    "forks_count": 111
  },
  {
    "full_name": "django/django",
    "stargazers_count": 64296,
    "open_issues_count": 154,
    "forks_count": 27168
  },
  {
    "full_name": "peaceiris/actions-gh-pages",
    "stargazers_count": 3093,
    "open_issues_count": 47,
    "forks_count": 235
  },
  {
    "full_name": "Frozen-Flask/Frozen-Flask",
    "stargazers_count": 716,
    "open_issues_count": 25,
    "forks_count": 70
  },
  {
    "full_name": "mikeckennedy/jinja_partials",
    "stargazers_count": 65,
    "open_issues_count": 1,
    "forks_count": 1
  },
  {
    "full_name": "WardPearce/thanker",
    "stargazers_count": 25,
    "open_issues_count": 0,
    "forks_count": 2
  },
  {
    "full_name": "willmcgugan/rich",
    "stargazers_count": 37739,
    "open_issues_count": 63,
    "forks_count": 1247
  },
  {
    "full_name": "pypa/pip",
    "stargazers_count": 8009,
    "open_issues_count": 977,
    "forks_count": 2621
  },
  {
    "full_name": "quantifiedcode/python-anti-patterns",
    "stargazers_count": 1588,
    "open_issues_count": 33,
    "forks_count": 248
  },
  {
    "full_name": "cmderdev/cmder",
    "stargazers_count": 23559,
    "open_issues_count": 11,
    "forks_count": 1944
  },
  {
    "full_name": "faif/python-patterns",
    "stargazers_count": 31478,
    "open_issues_count": 11,
    "forks_count": 6326
  },
  {
    "full_name": "justmedude/pylotoncycle",
    "stargazers_count": 28,
    "open_issues_count": 0,
    "forks_count": 11
  },
  {
    "full_name": "GamestonkTerminal/GamestonkTerminal",
    "stargazers_count": 12047,
    "open_issues_count": 60,
    "forks_count": 1292
  },
  {
    "full_name": "dwisiswant0/apkleaks",
    "stargazers_count": 2983,
    "open_issues_count": 10,
    "forks_count": 333
  },
  {
    "full_name": "arrow-py/arrow",
    "stargazers_count": 7897,
    "open_issues_count": 79,
    "forks_count": 618
  },
  {
    "full_name": "iam-abbas/Reddit-Stock-Trends",
    "stargazers_count": 1482,
    "open_issues_count": 17,
    "forks_count": 203
  },
  {
    "full_name": "openmainframeproject/cobol-programming-course",
    "stargazers_count": 2230,
    "open_issues_count": 12,
    "forks_count": 485
  }
]